{"CTRL_SECT_":257,"CTRL_SECT_KEY":"CS_257","route":"SH_87_","county":"GALVESTON","baseline_window":"2026-01-01 to 2026-01-21","event_window":"2026-01-22 to 2026-01-27","recovery_window":"2026-01-28 to 2026-02-03","time_to_80_hours":11.0,"time_to_90_hours":11.0,"resistance":0.795262,"absorption":1.0,"recovery":0.372091,"observed_resilience_impactfocused":0.771365,"series":[{"timestamp":"2026-01-24T09:00:00","q":0.8421,"phase":"event"},{"timestamp":"2026-01-24T16:00:00","q":0.7273,"phase":"event"},{"timestamp":"2026-01-25T11:00:00","q":0.4651,"phase":"event"},{"timestamp":"2026-01-25T12:00:00","q":1.2414,"phase":"event"},{"timestamp":"2026-01-26T10:00:00","q":1.5,"phase":"event"},{"timestamp":"2026-01-28T11:00:00","q":1.1893,"phase":"recovery"},{"timestamp":"2026-01-29T20:00:00","q":1.5,"phase":"recovery"},{"timestamp":"2026-01-30T11:00:00","q":0.1878,"phase":"recovery"},{"timestamp":"2026-01-31T21:00:00","q":0.3158,"phase":"recovery"},{"timestamp":"2026-02-02T11:00:00","q":1.0015,"phase":"recovery"},{"timestamp":"2026-02-02T13:00:00","q":0.8421,"phase":"recovery"}]}