{"CTRL_SECT_":520196,"CTRL_SECT_KEY":"CS_520196","route":"RM_32_","county":"BLANCO","baseline_window":"2026-01-01 to 2026-01-21","event_window":"2026-01-22 to 2026-01-27","recovery_window":"2026-01-28 to 2026-02-03","time_to_80_hours":4.0,"time_to_90_hours":4.0,"resistance":0.918982,"absorption":0.838542,"recovery":0.764364,"observed_resilience_impactfocused":0.848151,"series":[{"timestamp":"2026-01-22T00:00:00","q":0.9859,"phase":"event"},{"timestamp":"2026-01-22T02:00:00","q":1.0142,"phase":"event"},{"timestamp":"2026-01-22T03:00:00","q":0.9656,"phase":"event"},{"timestamp":"2026-01-22T04:00:00","q":1.0041,"phase":"event"},{"timestamp":"2026-01-22T05:00:00","q":0.5072,"phase":"event"},{"timestamp":"2026-01-22T06:00:00","q":0.872,"phase":"event"},{"timestamp":"2026-01-22T07:00:00","q":0.6663,"phase":"event"},{"timestamp":"2026-01-22T08:00:00","q":0.7104,"phase":"event"},{"timestamp":"2026-01-22T09:00:00","q":1.0498,"phase":"event"},{"timestamp":"2026-01-22T10:00:00","q":0.9102,"phase":"event"},{"timestamp":"2026-01-22T11:00:00","q":0.9184,"phase":"event"},{"timestamp":"2026-01-22T12:00:00","q":1.1606,"phase":"event"},{"timestamp":"2026-01-22T13:00:00","q":0.9336,"phase":"event"},{"timestamp":"2026-01-22T14:00:00","q":0.9146,"phase":"event"},{"timestamp":"2026-01-22T15:00:00","q":0.7499,"phase":"event"},{"timestamp":"2026-01-22T16:00:00","q":0.5931,"phase":"event"},{"timestamp":"2026-01-22T17:00:00","q":1.1163,"phase":"event"},{"timestamp":"2026-01-22T18:00:00","q":0.7395,"phase":"event"},{"timestamp":"2026-01-22T19:00:00","q":0.8939,"phase":"event"},{"timestamp":"2026-01-22T20:00:00","q":1.0978,"phase":"event"},{"timestamp":"2026-01-22T21:00:00","q":1.104,"phase":"event"},{"timestamp":"2026-01-22T22:00:00","q":0.6546,"phase":"event"},{"timestamp":"2026-01-22T23:00:00","q":0.7296,"phase":"event"},{"timestamp":"2026-01-23T00:00:00","q":0.7846,"phase":"event"},{"timestamp":"2026-01-23T02:00:00","q":0.8743,"phase":"event"},{"timestamp":"2026-01-23T03:00:00","q":0.9263,"phase":"event"},{"timestamp":"2026-01-23T04:00:00","q":1.0368,"phase":"event"},{"timestamp":"2026-01-23T05:00:00","q":1.0301,"phase":"event"},{"timestamp":"2026-01-23T06:00:00","q":1.1896,"phase":"event"},{"timestamp":"2026-01-23T07:00:00","q":1.0788,"phase":"event"},{"timestamp":"2026-01-23T08:00:00","q":1.1608,"phase":"event"},{"timestamp":"2026-01-23T09:00:00","q":1.3498,"phase":"event"},{"timestamp":"2026-01-23T10:00:00","q":0.9792,"phase":"event"},{"timestamp":"2026-01-23T11:00:00","q":1.1204,"phase":"event"},{"timestamp":"2026-01-23T12:00:00","q":0.8827,"phase":"event"},{"timestamp":"2026-01-23T13:00:00","q":0.9098,"phase":"event"},{"timestamp":"2026-01-23T14:00:00","q":1.5,"phase":"event"},{"timestamp":"2026-01-23T15:00:00","q":1.1318,"phase":"event"},{"timestamp":"2026-01-23T16:00:00","q":0.7454,"phase":"event"},{"timestamp":"2026-01-23T17:00:00","q":0.837,"phase":"event"},{"timestamp":"2026-01-23T18:00:00","q":1.5,"phase":"event"},{"timestamp":"2026-01-23T19:00:00","q":1.4589,"phase":"event"},{"timestamp":"2026-01-23T20:00:00","q":1.3766,"phase":"event"},{"timestamp":"2026-01-23T21:00:00","q":1.1763,"phase":"event"},{"timestamp":"2026-01-23T22:00:00","q":0.3883,"phase":"event"},{"timestamp":"2026-01-23T23:00:00","q":0.7906,"phase":"event"},{"timestamp":"2026-01-24T00:00:00","q":0.9451,"phase":"event"},{"timestamp":"2026-01-24T02:00:00","q":1.0492,"phase":"event"},{"timestamp":"2026-01-24T03:00:00","q":1.0702,"phase":"event"},{"timestamp":"2026-01-24T04:00:00","q":0.9746,"phase":"event"},{"timestamp":"2026-01-24T05:00:00","q":0.9739,"phase":"event"},{"timestamp":"2026-01-24T07:00:00","q":0.9802,"phase":"event"},{"timestamp":"2026-01-24T08:00:00","q":1.5,"phase":"event"},{"timestamp":"2026-01-24T09:00:00","q":1.5,"phase":"event"},{"timestamp":"2026-01-24T10:00:00","q":1.2756,"phase":"event"},{"timestamp":"2026-01-24T11:00:00","q":0.951,"phase":"event"},{"timestamp":"2026-01-24T12:00:00","q":1.5,"phase":"event"},{"timestamp":"2026-01-24T13:00:00","q":1.0425,"phase":"event"},{"timestamp":"2026-01-24T14:00:00","q":1.1642,"phase":"event"},{"timestamp":"2026-01-24T15:00:00","q":1.1748,"phase":"event"},{"timestamp":"2026-01-24T16:00:00","q":1.4335,"phase":"event"},{"timestamp":"2026-01-24T17:00:00","q":1.4949,"phase":"event"},{"timestamp":"2026-01-24T19:00:00","q":0.789,"phase":"event"},{"timestamp":"2026-01-24T20:00:00","q":1.5,"phase":"event"},{"timestamp":"2026-01-24T21:00:00","q":0.783,"phase":"event"},{"timestamp":"2026-01-24T22:00:00","q":0.1745,"phase":"event"},{"timestamp":"2026-01-24T23:00:00","q":0.7016,"phase":"event"},{"timestamp":"2026-01-25T05:00:00","q":0.5456,"phase":"event"},{"timestamp":"2026-01-25T09:00:00","q":0.9497,"phase":"event"},{"timestamp":"2026-01-25T10:00:00","q":0.8367,"phase":"event"},{"timestamp":"2026-01-25T11:00:00","q":1.1947,"phase":"event"},{"timestamp":"2026-01-25T12:00:00","q":0.9316,"phase":"event"},{"timestamp":"2026-01-25T13:00:00","q":0.896,"phase":"event"},{"timestamp":"2026-01-25T14:00:00","q":0.818,"phase":"event"},{"timestamp":"2026-01-25T15:00:00","q":0.9396,"phase":"event"},{"timestamp":"2026-01-25T16:00:00","q":1.3608,"phase":"event"},{"timestamp":"2026-01-25T17:00:00","q":1.0515,"phase":"event"},{"timestamp":"2026-01-25T18:00:00","q":1.5,"phase":"event"},{"timestamp":"2026-01-25T21:00:00","q":0.7812,"phase":"event"},{"timestamp":"2026-01-26T01:00:00","q":0.9973,"phase":"event"},{"timestamp":"2026-01-26T02:00:00","q":0.7179,"phase":"event"},{"timestamp":"2026-01-26T04:00:00","q":1.0923,"phase":"event"},{"timestamp":"2026-01-26T05:00:00","q":0.8358,"phase":"event"},{"timestamp":"2026-01-26T06:00:00","q":1.0246,"phase":"event"},{"timestamp":"2026-01-26T07:00:00","q":1.5,"phase":"event"},{"timestamp":"2026-01-26T08:00:00","q":1.0816,"phase":"event"},{"timestamp":"2026-01-26T09:00:00","q":1.4546,"phase":"event"},{"timestamp":"2026-01-26T10:00:00","q":1.4283,"phase":"event"},{"timestamp":"2026-01-26T11:00:00","q":1.3657,"phase":"event"},{"timestamp":"2026-01-26T12:00:00","q":1.4715,"phase":"event"},{"timestamp":"2026-01-26T13:00:00","q":0.9905,"phase":"event"},{"timestamp":"2026-01-26T14:00:00","q":0.7958,"phase":"event"},{"timestamp":"2026-01-26T15:00:00","q":1.3879,"phase":"event"},{"timestamp":"2026-01-26T16:00:00","q":1.4227,"phase":"event"},{"timestamp":"2026-01-26T17:00:00","q":1.5,"phase":"event"},{"timestamp":"2026-01-26T18:00:00","q":0.9112,"phase":"event"},{"timestamp":"2026-01-26T19:00:00","q":1.2726,"phase":"event"},{"timestamp":"2026-01-26T20:00:00","q":1.0494,"phase":"event"},{"timestamp":"2026-01-26T21:00:00","q":0.7011,"phase":"event"},{"timestamp":"2026-01-26T22:00:00","q":1.0852,"phase":"event"},{"timestamp":"2026-01-27T04:00:00","q":1.0297,"phase":"event"},{"timestamp":"2026-01-27T05:00:00","q":1.5,"phase":"event"},{"timestamp":"2026-01-27T06:00:00","q":1.0637,"phase":"event"},{"timestamp":"2026-01-27T07:00:00","q":1.5,"phase":"event"},{"timestamp":"2026-01-27T08:00:00","q":0.9869,"phase":"event"},{"timestamp":"2026-01-27T09:00:00","q":1.3994,"phase":"event"},{"timestamp":"2026-01-27T10:00:00","q":1.2783,"phase":"event"},{"timestamp":"2026-01-27T11:00:00","q":1.0484,"phase":"event"},{"timestamp":"2026-01-27T12:00:00","q":0.6109,"phase":"event"},{"timestamp":"2026-01-27T13:00:00","q":1.193,"phase":"event"},{"timestamp":"2026-01-27T14:00:00","q":0.86,"phase":"event"},{"timestamp":"2026-01-27T15:00:00","q":0.617,"phase":"event"},{"timestamp":"2026-01-27T16:00:00","q":0.8564,"phase":"event"},{"timestamp":"2026-01-27T17:00:00","q":1.4063,"phase":"event"},{"timestamp":"2026-01-27T18:00:00","q":1.0992,"phase":"event"},{"timestamp":"2026-01-27T19:00:00","q":0.9968,"phase":"event"},{"timestamp":"2026-01-27T20:00:00","q":0.647,"phase":"event"},{"timestamp":"2026-01-27T21:00:00","q":1.445,"phase":"event"},{"timestamp":"2026-01-27T22:00:00","q":0.8434,"phase":"event"},{"timestamp":"2026-01-27T23:00:00","q":1.053,"phase":"event"},{"timestamp":"2026-01-28T00:00:00","q":0.7846,"phase":"recovery"},{"timestamp":"2026-01-28T04:00:00","q":1.104,"phase":"recovery"},{"timestamp":"2026-01-28T05:00:00","q":1.3411,"phase":"recovery"},{"timestamp":"2026-01-28T06:00:00","q":0.7272,"phase":"recovery"},{"timestamp":"2026-01-28T07:00:00","q":0.9521,"phase":"recovery"},{"timestamp":"2026-01-28T08:00:00","q":0.8793,"phase":"recovery"},{"timestamp":"2026-01-28T09:00:00","q":0.8505,"phase":"recovery"},{"timestamp":"2026-01-28T10:00:00","q":0.9809,"phase":"recovery"},{"timestamp":"2026-01-28T11:00:00","q":1.1091,"phase":"recovery"},{"timestamp":"2026-01-28T12:00:00","q":0.951,"phase":"recovery"},{"timestamp":"2026-01-28T13:00:00","q":0.7677,"phase":"recovery"},{"timestamp":"2026-01-28T14:00:00","q":1.2243,"phase":"recovery"},{"timestamp":"2026-01-28T15:00:00","q":0.611,"phase":"recovery"},{"timestamp":"2026-01-28T16:00:00","q":1.1671,"phase":"recovery"},{"timestamp":"2026-01-28T17:00:00","q":0.8481,"phase":"recovery"},{"timestamp":"2026-01-28T18:00:00","q":0.7957,"phase":"recovery"},{"timestamp":"2026-01-28T19:00:00","q":0.7706,"phase":"recovery"},{"timestamp":"2026-01-28T20:00:00","q":0.9295,"phase":"recovery"},{"timestamp":"2026-01-28T21:00:00","q":1.436,"phase":"recovery"},{"timestamp":"2026-01-28T22:00:00","q":1.1357,"phase":"recovery"},{"timestamp":"2026-01-29T02:00:00","q":0.8329,"phase":"recovery"},{"timestamp":"2026-01-29T04:00:00","q":0.9199,"phase":"recovery"},{"timestamp":"2026-01-29T05:00:00","q":0.752,"phase":"recovery"},{"timestamp":"2026-01-29T06:00:00","q":0.8866,"phase":"recovery"},{"timestamp":"2026-01-29T07:00:00","q":0.896,"phase":"recovery"},{"timestamp":"2026-01-29T08:00:00","q":0.6556,"phase":"recovery"},{"timestamp":"2026-01-29T09:00:00","q":1.0855,"phase":"recovery"},{"timestamp":"2026-01-29T10:00:00","q":1.1026,"phase":"recovery"},{"timestamp":"2026-01-29T11:00:00","q":0.7058,"phase":"recovery"},{"timestamp":"2026-01-29T12:00:00","q":0.9696,"phase":"recovery"},{"timestamp":"2026-01-29T13:00:00","q":0.6624,"phase":"recovery"},{"timestamp":"2026-01-29T14:00:00","q":0.994,"phase":"recovery"},{"timestamp":"2026-01-29T15:00:00","q":0.8001,"phase":"recovery"},{"timestamp":"2026-01-29T16:00:00","q":1.0406,"phase":"recovery"},{"timestamp":"2026-01-29T17:00:00","q":0.9192,"phase":"recovery"},{"timestamp":"2026-01-29T18:00:00","q":0.5433,"phase":"recovery"},{"timestamp":"2026-01-29T19:00:00","q":0.8796,"phase":"recovery"},{"timestamp":"2026-01-29T20:00:00","q":1.2252,"phase":"recovery"},{"timestamp":"2026-01-29T21:00:00","q":0.6988,"phase":"recovery"},{"timestamp":"2026-01-29T22:00:00","q":1.0283,"phase":"recovery"},{"timestamp":"2026-01-29T23:00:00","q":0.9845,"phase":"recovery"},{"timestamp":"2026-01-30T00:00:00","q":0.3313,"phase":"recovery"},{"timestamp":"2026-01-30T01:00:00","q":1.3289,"phase":"recovery"},{"timestamp":"2026-01-30T03:00:00","q":0.777,"phase":"recovery"},{"timestamp":"2026-01-30T04:00:00","q":1.2,"phase":"recovery"},{"timestamp":"2026-01-30T05:00:00","q":0.6574,"phase":"recovery"},{"timestamp":"2026-01-30T06:00:00","q":0.7332,"phase":"recovery"},{"timestamp":"2026-01-30T07:00:00","q":0.9895,"phase":"recovery"},{"timestamp":"2026-01-30T08:00:00","q":1.3695,"phase":"recovery"},{"timestamp":"2026-01-30T09:00:00","q":1.0712,"phase":"recovery"},{"timestamp":"2026-01-30T10:00:00","q":1.4933,"phase":"recovery"},{"timestamp":"2026-01-30T11:00:00","q":0.7607,"phase":"recovery"},{"timestamp":"2026-01-30T12:00:00","q":0.9774,"phase":"recovery"},{"timestamp":"2026-01-30T13:00:00","q":1.0234,"phase":"recovery"},{"timestamp":"2026-01-30T14:00:00","q":0.9197,"phase":"recovery"},{"timestamp":"2026-01-30T15:00:00","q":0.7706,"phase":"recovery"},{"timestamp":"2026-01-30T16:00:00","q":1.1251,"phase":"recovery"},{"timestamp":"2026-01-30T17:00:00","q":1.0213,"phase":"recovery"},{"timestamp":"2026-01-30T18:00:00","q":1.4477,"phase":"recovery"},{"timestamp":"2026-01-30T19:00:00","q":1.0999,"phase":"recovery"},{"timestamp":"2026-01-30T20:00:00","q":0.9912,"phase":"recovery"},{"timestamp":"2026-01-30T21:00:00","q":1.252,"phase":"recovery"},{"timestamp":"2026-01-30T22:00:00","q":1.221,"phase":"recovery"},{"timestamp":"2026-01-30T23:00:00","q":0.8976,"phase":"recovery"},{"timestamp":"2026-01-31T00:00:00","q":1.2238,"phase":"recovery"},{"timestamp":"2026-01-31T01:00:00","q":0.944,"phase":"recovery"},{"timestamp":"2026-01-31T04:00:00","q":1.1058,"phase":"recovery"},{"timestamp":"2026-01-31T05:00:00","q":0.6806,"phase":"recovery"},{"timestamp":"2026-01-31T06:00:00","q":0.8799,"phase":"recovery"},{"timestamp":"2026-01-31T07:00:00","q":1.1022,"phase":"recovery"},{"timestamp":"2026-01-31T08:00:00","q":1.4344,"phase":"recovery"},{"timestamp":"2026-01-31T09:00:00","q":1.2354,"phase":"recovery"},{"timestamp":"2026-01-31T10:00:00","q":1.1323,"phase":"recovery"},{"timestamp":"2026-01-31T11:00:00","q":1.0671,"phase":"recovery"},{"timestamp":"2026-01-31T12:00:00","q":0.8716,"phase":"recovery"},{"timestamp":"2026-01-31T13:00:00","q":0.7405,"phase":"recovery"},{"timestamp":"2026-01-31T14:00:00","q":0.9507,"phase":"recovery"},{"timestamp":"2026-01-31T15:00:00","q":0.6786,"phase":"recovery"},{"timestamp":"2026-01-31T16:00:00","q":0.8718,"phase":"recovery"},{"timestamp":"2026-01-31T17:00:00","q":0.9349,"phase":"recovery"},{"timestamp":"2026-01-31T18:00:00","q":0.9634,"phase":"recovery"},{"timestamp":"2026-01-31T19:00:00","q":0.3729,"phase":"recovery"},{"timestamp":"2026-01-31T20:00:00","q":1.2802,"phase":"recovery"},{"timestamp":"2026-01-31T21:00:00","q":0.584,"phase":"recovery"},{"timestamp":"2026-01-31T22:00:00","q":1.3198,"phase":"recovery"},{"timestamp":"2026-01-31T23:00:00","q":1.028,"phase":"recovery"},{"timestamp":"2026-02-01T00:00:00","q":0.8192,"phase":"recovery"},{"timestamp":"2026-02-01T01:00:00","q":0.6508,"phase":"recovery"},{"timestamp":"2026-02-01T02:00:00","q":0.8809,"phase":"recovery"},{"timestamp":"2026-02-01T04:00:00","q":1.1243,"phase":"recovery"},{"timestamp":"2026-02-01T06:00:00","q":1.0925,"phase":"recovery"},{"timestamp":"2026-02-01T07:00:00","q":1.2649,"phase":"recovery"},{"timestamp":"2026-02-01T08:00:00","q":0.9475,"phase":"recovery"},{"timestamp":"2026-02-01T09:00:00","q":1.0545,"phase":"recovery"},{"timestamp":"2026-02-01T10:00:00","q":0.9939,"phase":"recovery"},{"timestamp":"2026-02-01T11:00:00","q":0.9621,"phase":"recovery"},{"timestamp":"2026-02-01T12:00:00","q":0.9545,"phase":"recovery"},{"timestamp":"2026-02-01T13:00:00","q":0.9684,"phase":"recovery"},{"timestamp":"2026-02-01T14:00:00","q":0.9395,"phase":"recovery"},{"timestamp":"2026-02-01T15:00:00","q":1.2369,"phase":"recovery"},{"timestamp":"2026-02-01T16:00:00","q":0.9413,"phase":"recovery"},{"timestamp":"2026-02-01T17:00:00","q":0.9067,"phase":"recovery"},{"timestamp":"2026-02-01T18:00:00","q":0.851,"phase":"recovery"},{"timestamp":"2026-02-01T19:00:00","q":0.7657,"phase":"recovery"},{"timestamp":"2026-02-01T20:00:00","q":1.1953,"phase":"recovery"},{"timestamp":"2026-02-01T21:00:00","q":1.2295,"phase":"recovery"},{"timestamp":"2026-02-01T22:00:00","q":0.3004,"phase":"recovery"},{"timestamp":"2026-02-01T23:00:00","q":1.0018,"phase":"recovery"},{"timestamp":"2026-02-02T00:00:00","q":0.9638,"phase":"recovery"},{"timestamp":"2026-02-02T02:00:00","q":0.9915,"phase":"recovery"},{"timestamp":"2026-02-02T04:00:00","q":1.1302,"phase":"recovery"},{"timestamp":"2026-02-02T05:00:00","q":1.2941,"phase":"recovery"},{"timestamp":"2026-02-02T06:00:00","q":0.9643,"phase":"recovery"},{"timestamp":"2026-02-02T07:00:00","q":1.1178,"phase":"recovery"},{"timestamp":"2026-02-02T08:00:00","q":1.0397,"phase":"recovery"},{"timestamp":"2026-02-02T09:00:00","q":0.7807,"phase":"recovery"},{"timestamp":"2026-02-02T10:00:00","q":0.8576,"phase":"recovery"},{"timestamp":"2026-02-02T11:00:00","q":0.679,"phase":"recovery"},{"timestamp":"2026-02-02T12:00:00","q":1.1767,"phase":"recovery"},{"timestamp":"2026-02-02T13:00:00","q":0.9822,"phase":"recovery"},{"timestamp":"2026-02-02T14:00:00","q":0.6072,"phase":"recovery"},{"timestamp":"2026-02-02T15:00:00","q":1.0717,"phase":"recovery"},{"timestamp":"2026-02-02T16:00:00","q":0.7459,"phase":"recovery"},{"timestamp":"2026-02-02T17:00:00","q":0.5512,"phase":"recovery"},{"timestamp":"2026-02-02T18:00:00","q":0.5783,"phase":"recovery"},{"timestamp":"2026-02-02T19:00:00","q":0.8384,"phase":"recovery"},{"timestamp":"2026-02-02T20:00:00","q":0.4576,"phase":"recovery"},{"timestamp":"2026-02-02T21:00:00","q":0.9101,"phase":"recovery"},{"timestamp":"2026-02-02T22:00:00","q":1.0849,"phase":"recovery"},{"timestamp":"2026-02-02T23:00:00","q":1.0067,"phase":"recovery"},{"timestamp":"2026-02-03T00:00:00","q":0.991,"phase":"recovery"},{"timestamp":"2026-02-03T01:00:00","q":1.1017,"phase":"recovery"},{"timestamp":"2026-02-03T02:00:00","q":1.2415,"phase":"recovery"},{"timestamp":"2026-02-03T03:00:00","q":0.9899,"phase":"recovery"},{"timestamp":"2026-02-03T04:00:00","q":1.0456,"phase":"recovery"},{"timestamp":"2026-02-03T05:00:00","q":1.0301,"phase":"recovery"},{"timestamp":"2026-02-03T06:00:00","q":0.5805,"phase":"recovery"},{"timestamp":"2026-02-03T07:00:00","q":0.8189,"phase":"recovery"},{"timestamp":"2026-02-03T08:00:00","q":0.973,"phase":"recovery"},{"timestamp":"2026-02-03T09:00:00","q":0.9901,"phase":"recovery"},{"timestamp":"2026-02-03T10:00:00","q":1.2314,"phase":"recovery"},{"timestamp":"2026-02-03T11:00:00","q":1.1015,"phase":"recovery"},{"timestamp":"2026-02-03T12:00:00","q":1.0128,"phase":"recovery"},{"timestamp":"2026-02-03T13:00:00","q":1.5,"phase":"recovery"},{"timestamp":"2026-02-03T14:00:00","q":1.108,"phase":"recovery"},{"timestamp":"2026-02-03T15:00:00","q":1.3159,"phase":"recovery"},{"timestamp":"2026-02-03T16:00:00","q":0.7955,"phase":"recovery"},{"timestamp":"2026-02-03T17:00:00","q":0.9722,"phase":"recovery"},{"timestamp":"2026-02-03T18:00:00","q":1.1041,"phase":"recovery"},{"timestamp":"2026-02-03T19:00:00","q":0.8401,"phase":"recovery"},{"timestamp":"2026-02-03T20:00:00","q":0.7124,"phase":"recovery"},{"timestamp":"2026-02-03T21:00:00","q":0.8359,"phase":"recovery"},{"timestamp":"2026-02-03T22:00:00","q":1.0692,"phase":"recovery"}]}